odoo/addons/account_invoice_overdue_warn_sale/README.rst
odoo/addons/account_invoice_overdue_warn_sale/__init__.py
odoo/addons/account_invoice_overdue_warn_sale/__manifest__.py
odoo/addons/account_invoice_overdue_warn_sale/i18n/account_invoice_overdue_warn_sale.pot
odoo/addons/account_invoice_overdue_warn_sale/i18n/fr.po
odoo/addons/account_invoice_overdue_warn_sale/models/__init__.py
odoo/addons/account_invoice_overdue_warn_sale/models/sale_order.py
odoo/addons/account_invoice_overdue_warn_sale/readme/CONTRIBUTORS.rst
odoo/addons/account_invoice_overdue_warn_sale/readme/DESCRIPTION.rst
odoo/addons/account_invoice_overdue_warn_sale/static/description/icon.png
odoo/addons/account_invoice_overdue_warn_sale/static/description/index.html
odoo/addons/account_invoice_overdue_warn_sale/static/description/sale_order_overdue_invoice_warn.png
odoo/addons/account_invoice_overdue_warn_sale/views/sale_order.xml
odoo13_addon_account_invoice_overdue_warn_sale-13.0.1.0.1.dev4.dist-info/METADATA
odoo13_addon_account_invoice_overdue_warn_sale-13.0.1.0.1.dev4.dist-info/WHEEL
odoo13_addon_account_invoice_overdue_warn_sale-13.0.1.0.1.dev4.dist-info/top_level.txt
odoo13_addon_account_invoice_overdue_warn_sale-13.0.1.0.1.dev4.dist-info/RECORD
